blackbox_api/__init__.py
blackbox_api/blackbox.py
blackbox_api-1.0.0.dist-info/LICENSE
blackbox_api-1.0.0.dist-info/METADATA
blackbox_api-1.0.0.dist-info/WHEEL
blackbox_api-1.0.0.dist-info/top_level.txt
blackbox_api-1.0.0.dist-info/RECORD
