Metadata-Version: 2.1
Name: blackbox-api
Version: 1.0.0
Summary: Unofficial blackbox api library for python
Home-page: https://github.com/DogCompanyInc/blackbox-api
Author: dogie
Author-email: pavelt1234567890@gmail.com
Project-URL: GitHub, https://github.com/DogCompanyInc
Keywords: blackbox api chatGPT GPT dogie
Classifier: Programming Language :: Python :: 3.11
Classifier: License :: OSI Approved :: MIT License
Classifier: Operating System :: OS Independent
Requires-Python: >=3.6
License-File: LICENSE
Requires-Dist: requests >=2.25.1
Requires-Dist: json5
